Metadata-Version: 2.1
Name: graphql-pydantic-converter
Version: 1.2.2
Summary: Convert pydantic schema to pydantic datamodel and build request from it
License: Apache 2.0
Keywords: graphql,pydantic
Author: Jozef Volak
Author-email: jozef.volak@elisapolystar.com
Requires-Python: >=3.10,<4.0
Classifier: License :: Other/Proprietary License
Classifier: Programming Language :: Python :: 3
Classifier: Programming Language :: Python :: 3.10
Classifier: Programming Language :: Python :: 3.11
Requires-Dist: pydantic (>=2,<3)
Requires-Dist: requests (>=2.31.0,<3.0.0)
